papermerge/conf/__init__.py
papermerge/conf/settings.py
papermerge/core/__init__.py
papermerge/core/app_settings.py
papermerge/core/apps.py
papermerge/core/auth/__init__.py
papermerge/core/auth/decorators.py
papermerge/core/auth.py
papermerge/core/automate.py
papermerge/core/backup_restore/__init__.py
papermerge/core/backup_restore/backup.py
papermerge/core/backup_restore/restore.py
papermerge/core/backup_restore/serializers.py
papermerge/core/backup_restore/utils.py
papermerge/core/checks.py
papermerge/core/dynamic_preferences_registry.py
papermerge/core/exceptions.py
papermerge/core/lib/__init__.py
papermerge/core/lib/lang.py
papermerge/core/lib/mime.py
papermerge/core/lib/pagecount.py
papermerge/core/lib/path.py
papermerge/core/lib/runcmd.py
papermerge/core/lib/shortcuts.py
papermerge/core/lib/storage.py
papermerge/core/lib/tiff.py
papermerge/core/lib/utils.py
papermerge/core/lib/wrapper.py
papermerge/core/locale/de/LC_MESSAGES/django.po
papermerge/core/locale/fr/LC_MESSAGES/django.po
papermerge/core/management/__init__.py
papermerge/core/management/commands/__init__.py
papermerge/core/management/commands/backup.py
papermerge/core/management/commands/ocr.py
papermerge/core/management/commands/restore.py
papermerge/core/middleware/__init__.py
papermerge/core/middleware/timezone.py
papermerge/core/migrations/0001_initial.py
papermerge/core/migrations/0002_auto_20220619_0847.py
papermerge/core/migrations/0003_alter_basetreenode_polymorphic_ctype_and_more.py
papermerge/core/migrations/0004_remove_automate_dst_folder_remove_automate_tags_and_more.py
papermerge/core/migrations/0005_basetreenode_unique title per parent.py
papermerge/core/migrations/0006_alter_basetreenode_options_remove_basetreenode_level_and_more.py
papermerge/core/migrations/0007_basetreenode_parent_title_uniq_when_parent_is_null.py
papermerge/core/migrations/0008_remove_basetreenode_parent_title_uniq_when_parent_is_null_and_more.py
papermerge_core-2.1.5.dist-info/METADATA
papermerge_core-2.1.5.dist-info/WHEEL
papermerge_core-2.1.5.dist-info/LICENSE
papermerge_core-2.1.5.dist-info/RECORD
