Metadata-Version: 2.1
Name: papermerge-core
Version: 2.1.5
Summary: Open source document management system for digital archives
Home-page: https://www.papermerge.com/
License: Apache 2.0
Keywords: PDF,OCR,optical character recognition,PDF/A,scanning,dms,document-management,paperless,archives
Author: Eugen Ciur
Author-email: eugen@papermerge.com
Maintainer: Eugen Ciur
Maintainer-email: eugen@papermerge.com
Requires-Python: >=3.8,<3.11
Classifier: Environment :: Web Environment
Classifier: Framework :: Django
Classifier: License :: OSI Approved :: Apache Software License
Classifier: License :: Other/Proprietary License
Classifier: Operating System :: OS Independent
Classifier: Programming Language :: Python
Classifier: Programming Language :: Python :: 3
Classifier: Programming Language :: Python :: 3.8
Classifier: Programming Language :: Python :: 3.9
Classifier: Programming Language :: Python :: 3.10
Classifier: Programming Language :: Python :: 3
Requires-Dist: Whoosh (>=2.7.4,<3.0.0)
Requires-Dist: celery[gevent,redis] (>=5.2,<6.0)
Requires-Dist: channels (>=3.0,<4.0)
Requires-Dist: channels-redis (>=3.2,<4.0)
Requires-Dist: configula (>=0.5,<0.6)
Requires-Dist: daphne (>=3.0.2,<4.0.0)
Requires-Dist: django (>=4.0,<5.0)
Requires-Dist: django-celery-results (>=2.2,<3.0)
Requires-Dist: django-cors-headers (>=3.9.0,<4.0.0)
Requires-Dist: django-dynamic-preferences (>=1.13,<2.0)
Requires-Dist: django-haystack (>=3.2.1,<4.0.0)
Requires-Dist: django-modelcluster (>=6.0,<7.0)
Requires-Dist: django-rest-knox (>=4.2.0,<5.0.0)
Requires-Dist: django-taggit (>=3.0.0,<4.0.0)
Requires-Dist: django_filter (>=21.1,<22.0)
Requires-Dist: djangorestframework (>=3.13.1,<4.0.0)
Requires-Dist: djangorestframework-jsonapi (>=5.0.0,<6.0.0)
Requires-Dist: drf-spectacular (>=0.22.0,<0.23.0)
Requires-Dist: drf-spectacular-sidecar (>=2022.3.21,<2023.0.0)
Requires-Dist: elasticsearch (>=7,<8)
Requires-Dist: lxml (>=4.9.0,<5.0.0)
Requires-Dist: ocrmypdf (>=13.5.0,<14.0.0)
Requires-Dist: ocrmypdf-papermerge (>=0.4.5,<0.5.0)
Requires-Dist: pdf2image (>=1.16.0,<2.0.0)
Requires-Dist: persisting-theory (>=1.0,<2.0)
Requires-Dist: psycopg2 (>=2.9.2,<3.0.0)
Requires-Dist: psycopg2-binary (>=2.9.2,<3.0.0)
Requires-Dist: python-magic (>=0.4,<0.5)
Requires-Dist: pyyaml (>=6.0,<7.0)
Requires-Dist: redis (>=4.3.3,<5.0.0)
Requires-Dist: uWSGI (>=2.0.20,<3.0.0)
Requires-Dist: uritemplate (>=4.1.1,<5.0.0)
Requires-Dist: yapian-haystack (>=3.1.0,<4.0.0)
Project-URL: Documentation, https://docs.papermerge.io/
